setup.py
htd_custom_train/__init__.py
htd_custom_train/process_data.py
htd_custom_train/train.py
htd_custom_train/train_model.py
htd_custom_train/train_model_argparam.py
htd_custom_train/utils.py
htd_custom_train.egg-info/PKG-INFO
htd_custom_train.egg-info/SOURCES.txt
htd_custom_train.egg-info/dependency_links.txt
htd_custom_train.egg-info/top_level.txt