Metadata-Version: 2.1
Name: htd-custom-train
Version: 0.1
Summary: No description
Author: Duy
Author-email: duyht1.bhsoft@gmail.com
